paramak_tfcoil_rectroundcorner/__init__.py
paramak_tfcoil_rectroundcorner/core.py
paramak_tfcoil_rectroundcorner/test_module.py
paramak_tfcoil_rectroundcorner-0.0.2.dist-info/LICENSE
paramak_tfcoil_rectroundcorner-0.0.2.dist-info/METADATA
paramak_tfcoil_rectroundcorner-0.0.2.dist-info/WHEEL
paramak_tfcoil_rectroundcorner-0.0.2.dist-info/top_level.txt
paramak_tfcoil_rectroundcorner-0.0.2.dist-info/RECORD
