Metadata-Version: 2.1
Name: paramak-tfcoil-rectroundcorner
Version: 0.0.2
Summary: Package includes a new TF coil class with rounded corners for the paramak
Home-page: https://github.com/mateczentye/paramak_tfcoil_rectroundcorner
Author: Mate Czentye
Author-email: czentyemate@gmail.com
License: MIT
Platform: UNKNOWN
